oncvpsp_tools/__init__.py
oncvpsp_tools/__main__.py
oncvpsp_tools/api.py
oncvpsp_tools/cli.py
oncvpsp_tools/input.py
oncvpsp_tools/output.py
oncvpsp_tools/py.typed
oncvpsp_tools/utils.py
oncvpsp_tools/version.py
oncvpsp_tools-0.0.3.dist-info/LICENSE
oncvpsp_tools-0.0.3.dist-info/METADATA
oncvpsp_tools-0.0.3.dist-info/WHEEL
oncvpsp_tools-0.0.3.dist-info/entry_points.txt
oncvpsp_tools-0.0.3.dist-info/top_level.txt
oncvpsp_tools-0.0.3.dist-info/RECORD
