Metadata-Version: 2.1
Name: oncvpsp-tools
Version: 0.0.3
Summary: Tools for handling input and output files of oncvpsp.x
Home-page: https://github.com/pseudopotential-tools/oncvpsp-tools
Download-URL: https://github.com/pseudopotential-tools/oncvpsp-tools/releases
Author: Edward Linscott
Author-email: edwardlinscott@gmail.com
Maintainer: Edward Linscott
Maintainer-email: edwardlinscott@gmail.com
License: MIT
Project-URL: Tracker, https://github.com/pseudopotential-tools/oncvpsp-tools/issues
Project-URL: Source, https://github.com/pseudopotential-tools/oncvpsp-tools
Project-URL: Documentation, https://oncvpsp_tools.readthedocs.io
Keywords: snekpack,cookiecutter,pseudopotentials,oncvpsp
Classifier: Development Status :: 1 - Planning
Classifier: Environment :: Console
Classifier: Intended Audience :: Developers
Classifier: License :: OSI Approved :: MIT License
Classifier: Operating System :: OS Independent
Classifier: Framework :: Pytest
Classifier: Framework :: tox
Classifier: Framework :: Sphinx
Classifier: Programming Language :: Python
Classifier: Programming Language :: Python :: 3.8
Classifier: Programming Language :: Python :: 3.9
Classifier: Programming Language :: Python :: 3.10
Classifier: Programming Language :: Python :: 3.11
Classifier: Programming Language :: Python :: 3 :: Only
Requires-Python: >=3.8
License-File: LICENSE
Requires-Dist: more-itertools
Requires-Dist: tqdm
Requires-Dist: click
Requires-Dist: more-click
Requires-Dist: numpy
Requires-Dist: typing
Requires-Dist: matplotlib
Provides-Extra: docs
Requires-Dist: sphinx ==7.1 ; extra == 'docs'
Requires-Dist: sphinx-rtd-theme ; extra == 'docs'
Requires-Dist: sphinx-click ; extra == 'docs'
Requires-Dist: sphinx-automodapi ; extra == 'docs'
Requires-Dist: sphinx-autodoc-typehints ; extra == 'docs'
Provides-Extra: tests
Requires-Dist: pytest ; extra == 'tests'
Requires-Dist: coverage ; extra == 'tests'
